fonts/Quicksand-Bold.ttf
fonts/Quicksand-Light.ttf
fonts/Quicksand-Medium.ttf
fonts/Quicksand-Regular.ttf
fonts/__init__.py
niceplot/__init__.py
niceplot/base.py
niceplot/example_mpl.py
niceplot/helper.py
niceplot/plot.py
niceplot/styla.py
niceplot/swarmbox.py
niceplot/utils.py
niceplot-0.0.1.6.dist-info/DESCRIPTION.rst
niceplot-0.0.1.6.dist-info/METADATA
niceplot-0.0.1.6.dist-info/RECORD
niceplot-0.0.1.6.dist-info/WHEEL
niceplot-0.0.1.6.dist-info/metadata.json
niceplot-0.0.1.6.dist-info/top_level.txt
