Metadata-Version: 2.0
Name: niceplot
Version: 0.0.1.6
Summary: "Hey, that's a nice plot!"
Home-page: https://pypi.python.org/pypi/pytrack-analysis
Author: Dennis Goldschmidt
Author-email: dennis.goldschmidt@neuro.fchampalimaud.org
License: GPLv3
Keywords: visualization,data analysis,matplotlib
Platform: Windows10Pro
Platform: MacOSX-ElCapitan
Classifier: Development Status :: 1 - Planning
Classifier: Operating System :: MacOS :: MacOS X
Classifier: Topic :: Utilities
Classifier: Topic :: Scientific/Engineering :: Visualization
Classifier: License :: OSI Approved :: GNU General Public License v3 (GPLv3)
Classifier: Programming Language :: Python :: 3.6
Requires-Python: >=3.6
